setup.cfg
setup.py
effortless_bootstrap_web_form_monkey_patch/__init__.py
effortless_bootstrap_web_form_monkey_patch/effortless_bootstrap_web_form_monkey_patch.py
effortless_bootstrap_web_form_monkey_patch.egg-info/PKG-INFO
effortless_bootstrap_web_form_monkey_patch.egg-info/SOURCES.txt
effortless_bootstrap_web_form_monkey_patch.egg-info/dependency_links.txt
effortless_bootstrap_web_form_monkey_patch.egg-info/not-zip-safe
effortless_bootstrap_web_form_monkey_patch.egg-info/requires.txt
effortless_bootstrap_web_form_monkey_patch.egg-info/top_level.txt