Metadata-Version: 1.1
Name: effortless-bootstrap-web-form-monkey-patch
Version: 0.1
Summary: Patch the old Form classes in web.py to create Bootstrap-compatible forms
Home-page: http://github.com/jmcguire/effortless_bootstrap_web_form_monkey_patch
Author: Justin McGuire
Author-email: jm@landedstar.com
License: MIT
Keywords: web form bootstrap
Platform: UNKNOWN
Classifier: Development Status :: 3 - Alpha
Classifier: License :: OSI Approved :: MIT License
Classifier: Programming Language :: Python :: 2.7
Classifier: Topic :: Internet :: WWW/HTTP :: WSGI
